<?xml version="1.0" encoding="UTF-8" standalone="yes"?>
<OrderForm>
<POData>
<AdditionalSigner/>
<countryCode>AU</countryCode>
<Comments>
<body xmlns="http://www.w3.org/1999/xhtml" xmlns:xfa="http://www.xfa.org/schema/xfa-data/1.0/" xfa:APIVersion="2.6.7185.0">Comes with Pearson Pallet Forks, no bucket. Freight Price to be confirmed and shared by customer Delivery approximately 3 weeks time Rear and Front wheels to be shifted out.</body>
</Comments>
<Equipment>
<ServiceAgreementAccepted>
<AgreementKey>203869</AgreementKey>
<Amount>
<Cents>00</Cents>
<Doller>$290</Doller>
</Amount>
<Description>+ package 03</Description>
<Quantity>1</Quantity>
</ServiceAgreementAccepted>
<ServiceAgreementAccepted>
<AgreementKey>765498</AgreementKey>
<AgreementType>PREPAID</AgreementType>
<Amount>
<Cents>00</Cents>
<Doller>$1,106</Doller>
</Amount>
<Description>+ PowerGard Protection :Sprayer,R4045,New Units - still within basic warranty,Limited - Engine &amp; Powertrain,New - Grace Period: Under 95 days &amp; 100 hours,24 Total Months Or 1000 Total Hours,AU,500.00,13-Apr-2016</Description>
<Quantity>1</Quantity>
</ServiceAgreementAccepted>
<ServiceAgreementAccepted>
<AgreementKey>765495</AgreementKey>
<AgreementType>INCLUDED</AgreementType>
<Amount>
<Cents>00</Cents>
<Doller>$45</Doller>
</Amount>
<Description>+ Support plan new 01</Description>
<Quantity>1</Quantity>
</ServiceAgreementAccepted>
<ServiceAgreementAccepted>
<AgreementKey>765496</AgreementKey>
<AgreementType>PREPAID</AgreementType>
<Amount>
<Cents>55</Cents>
<Doller>$1,500</Doller>
</Amount>
<Description>+ Rajesh V. Test Service Plan</Description>
<Quantity>1</Quantity>
</ServiceAgreementAccepted>
<Amount>
<Cents>00</Cents>
<Doller>$523,449</Doller>
</Amount>
<ServiceAgreementDeclined>
<AgreementKey>203870</AgreementKey>
<Description>- package 02</Description>
<Quantity>1</Quantity>
</ServiceAgreementDeclined>
<ServiceAgreementDeclined>
<AgreementKey>765497</AgreementKey>
<AgreementType>PREPAID</AgreementType>
<Description>- Jayanti.G test JDSC</Description>
<Quantity>1</Quantity>
</ServiceAgreementDeclined>
<ProductDescription>R4045 Self-Propelled Sprayer (Model Year 2016)</ProductDescription>
<quantity>1</quantity>
<isServiceOnlyEquipment>true</isServiceOnlyEquipment>
<Status>1</Status>
<TechnologyOptions>
<Amount>
<Cents>00</Cents>
<Doller>$0</Doller>
</Amount>
<Description>1835 </Description>
<isNew>X</isNew>
<Quantity>1</Quantity>
</TechnologyOptions>
<TechnologyOptions>
<Amount>
<Cents>00</Cents>
<Doller>$0</Doller>
</Amount>
<Description>1845 </Description>
<isNew>X</isNew>
<Quantity>1</Quantity>
</TechnologyOptions>
<TechnologyOptions>
<Amount>
<Cents>00</Cents>
<Doller>$0</Doller>
</Amount>
<Description>1900 </Description>
<isNew>X</isNew>
<Quantity>1</Quantity>
</TechnologyOptions>
</Equipment>
<Equipment>
<ServiceAgreementAccepted>
<AgreementKey>203872</AgreementKey>
<Amount>
<Cents>00</Cents>
<Doller>$246</Doller>
</Amount>
<Description>+ package 02</Description>
<Quantity>1</Quantity>
</ServiceAgreementAccepted>
<ServiceAgreementAccepted>
<AgreementKey>765511</AgreementKey>
<AgreementType>INCLUDED</AgreementType>
<Amount>
<Cents>00</Cents>
<Doller>$45</Doller>
</Amount>
<Description>+ Support plan new 01</Description>
<Quantity>1</Quantity>
</ServiceAgreementAccepted>
<ServiceAgreementAccepted>
<AgreementKey>765512</AgreementKey>
<AgreementType>PREPAID</AgreementType>
<Amount>
<Cents>55</Cents>
<Doller>$1,500</Doller>
</Amount>
<Description>+ Rajesh V. Test Service Plan</Description>
<Quantity>1</Quantity>
</ServiceAgreementAccepted>
<Amount>
<Cents>00</Cents>
<Doller>$523,449</Doller>
</Amount>
<ServiceAgreementDeclined>
<AgreementKey>203871</AgreementKey>
<Description>- package 03</Description>
<Quantity>1</Quantity>
</ServiceAgreementDeclined>
<ServiceAgreementDeclined>
<AgreementKey>765514</AgreementKey>
<AgreementType>PREPAID/ PAY AS YOU GO/ INCLUDED</AgreementType>
<Description>- DECLINED : PowerGard Protection :Sprayer,R4045,New Units - still within basic warranty,Limited - Engine &amp; Powertrain,New - Grace Period: Under 95 days &amp; 100 hours,24 Total Months Or 1500 Total Hours,AU,500.00,13-Apr-2016</Description>
<Quantity>1</Quantity>
</ServiceAgreementDeclined>
<ServiceAgreementDeclined>
<AgreementKey>765510</AgreementKey>
<AgreementType>INCLUDED</AgreementType>
<Description>- Support plan new 03</Description>
<Quantity>1</Quantity>
</ServiceAgreementDeclined>
<ServiceAgreementDeclined>
<AgreementKey>765513</AgreementKey>
<AgreementType>PREPAID</AgreementType>
<Description>- Jayanti.G test JDSC</Description>
<Quantity>1</Quantity>
</ServiceAgreementDeclined>
<ProductDescription>R4045 Self-Propelled Sprayer (Model Year 2016)</ProductDescription>
<quantity>1</quantity>
<isServiceOnlyEquipment>true</isServiceOnlyEquipment>
<Status>1</Status>
<TechnologyOptions>
<Amount>
<Cents>00</Cents>
<Doller>$0</Doller>
</Amount>
<Description>1835 </Description>
<isNew>X</isNew>
<Quantity>1</Quantity>
</TechnologyOptions>
<TechnologyOptions>
<Amount>
<Cents>00</Cents>
<Doller>$0</Doller>
</Amount>
<Description>1845 </Description>
<isNew>X</isNew>
<Quantity>1</Quantity>
</TechnologyOptions>
<TechnologyOptions>
<Amount>
<Cents>00</Cents>
<Doller>$0</Doller>
</Amount>
<Description>1900 </Description>
<isNew>X</isNew>
<Quantity>1</Quantity>
</TechnologyOptions>
</Equipment>
<Equipment>
<ServiceAgreementAccepted>
<AgreementKey>203946</AgreementKey>
<Amount>
<Cents>00</Cents>
<Doller>$175</Doller>
</Amount>
<Description>+ Test package</Description>
<Quantity>1</Quantity>
</ServiceAgreementAccepted>
<ServiceAgreementAccepted>
<AgreementKey>203867</AgreementKey>
<Amount>
<Cents>00</Cents>
<Doller>$600</Doller>
</Amount>
<Description>+ package 04</Description>
<Quantity>1</Quantity>
</ServiceAgreementAccepted>
<ServiceAgreementAccepted>
<AgreementKey>203868</AgreementKey>
<Amount>
<Cents>00</Cents>
<Doller>$440</Doller>
</Amount>
<Description>+ package 01</Description>
<Quantity>1</Quantity>
</ServiceAgreementAccepted>
<ServiceAgreementAccepted>
<AgreementKey>765483</AgreementKey>
<AgreementType>PAY AS YOU GO</AgreementType>
<Amount>
<Cents>00</Cents>
<Doller>$156</Doller>
</Amount>
<Description>+ Test Service plan for sale center 02</Description>
<Quantity>1</Quantity>
</ServiceAgreementAccepted>
<ServiceAgreementAccepted>
<AgreementKey>765482</AgreementKey>
<AgreementType>INCLUDED</AgreementType>
<Amount>
<Cents>00</Cents>
<Doller>$309</Doller>
</Amount>
<Description>+ Test Service plan for sale center 04</Description>
<Quantity>1</Quantity>
</ServiceAgreementAccepted>
<ProductDescription>Non Equipment Service Agreements</ProductDescription>
<isServiceOnlyEquipment>true</isServiceOnlyEquipment>
<Status>1</Status>
</Equipment>
<EquipmentDetail>
<ServiceAgreementAccepted>
<AgreementKey>203869</AgreementKey>
<Amount>
<Cents>00</Cents>
<Doller>$290</Doller>
</Amount>
<Description>+ package 03</Description>
<Quantity>1</Quantity>
</ServiceAgreementAccepted>
<ServiceAgreementAccepted>
<AgreementKey>765498</AgreementKey>
<AgreementType>PREPAID</AgreementType>
<Amount>
<Cents>00</Cents>
<Doller>$1,106</Doller>
</Amount>
<Description>+ PowerGard Protection :Sprayer,R4045,New Units - still within basic warranty,Limited - Engine &amp; Powertrain,New - Grace Period: Under 95 days &amp; 100 hours,24 Total Months Or 1000 Total Hours,AU,500.00,13-Apr-2016</Description>
<Quantity>1</Quantity>
</ServiceAgreementAccepted>
<ServiceAgreementAccepted>
<AgreementKey>765495</AgreementKey>
<AgreementType>INCLUDED</AgreementType>
<Amount>
<Cents>00</Cents>
<Doller>$45</Doller>
</Amount>
<Description>+ Support plan new 01</Description>
<Quantity>1</Quantity>
</ServiceAgreementAccepted>
<ServiceAgreementAccepted>
<AgreementKey>765496</AgreementKey>
<AgreementType>PREPAID</AgreementType>
<Amount>
<Cents>55</Cents>
<Doller>$1,500</Doller>
</Amount>
<Description>+ Rajesh V. Test Service Plan</Description>
<Quantity>1</Quantity>
</ServiceAgreementAccepted>
<Amount>
<Cents>00</Cents>
<Doller>$523,449</Doller>
</Amount>
<ServiceAgreementDeclined>
<AgreementKey>203870</AgreementKey>
<Description>- package 02</Description>
<Quantity>1</Quantity>
</ServiceAgreementDeclined>
<ServiceAgreementDeclined>
<AgreementKey>765497</AgreementKey>
<AgreementType>PREPAID</AgreementType>
<Description>- Jayanti.G test JDSC</Description>
<Quantity>1</Quantity>
</ServiceAgreementDeclined>
<Option>
<Code>0230</Code>
<Description></Description>
<Quantity>1</Quantity>
</Option>
<Option>
<Code>0448</Code>
<Description></Description>
<Quantity>1</Quantity>
</Option>
<Option>
<Code>188I</Code>
<Description></Description>
<Quantity>1</Quantity>
</Option>
<Option>
<Code>2310</Code>
<Description></Description>
<Quantity>1</Quantity>
</Option>
<Option>
<Code>2410</Code>
<Description></Description>
<Quantity>1</Quantity>
</Option>
<Option>
<Code>2854</Code>
<Description></Description>
<Quantity>1</Quantity>
</Option>
<Option>
<Code>7060</Code>
<Description></Description>
<Quantity>1</Quantity>
</Option>
<Option>
<Code>3542</Code>
<Description></Description>
<Quantity>1</Quantity>
</Option>
<Option>
<Code>4115</Code>
<Description></Description>
<Quantity>1</Quantity>
</Option>
<Option>
<Code>4210</Code>
<Description></Description>
<Quantity>1</Quantity>
</Option>
<Option>
<Code>4300</Code>
<Description></Description>
<Quantity>1</Quantity>
</Option>
<Option>
<Code>4050</Code>
<Description></Description>
<Quantity>1</Quantity>
</Option>
<Option>
<Code>5175</Code>
<Description></Description>
<Quantity>1</Quantity>
</Option>
<Option>
<Code>5465</Code>
<Description></Description>
<Quantity>1</Quantity>
</Option>
<Option>
<Code>5500</Code>
<Description></Description>
<Quantity>1</Quantity>
</Option>
<Option>
<Code>7540</Code>
<Description></Description>
<Quantity>1</Quantity>
</Option>
<Option>
<Code>7825</Code>
<Description></Description>
<Quantity>1</Quantity>
</Option>
<Option>
<Code>7901</Code>
<Description></Description>
<Quantity>1</Quantity>
</Option>
<Option>
<Code>7925</Code>
<Description></Description>
<Quantity>1</Quantity>
</Option>
<ProductDescription>R4045 Self-Propelled Sprayer (Model Year 2016)</ProductDescription>
<TechnologyOptions>
<Code>1835</Code>
<Name></Name>
<Quantity>1</Quantity>
</TechnologyOptions>
<TechnologyOptions>
<Code>1845</Code>
<Name></Name>
<Quantity>1</Quantity>
</TechnologyOptions>
<TechnologyOptions>
<Code>1900</Code>
<Name></Name>
<Quantity>1</Quantity>
</TechnologyOptions>
</EquipmentDetail>
<EquipmentDetail>
<ServiceAgreementAccepted>
<AgreementKey>203872</AgreementKey>
<Amount>
<Cents>00</Cents>
<Doller>$246</Doller>
</Amount>
<Description>+ package 02</Description>
<Quantity>1</Quantity>
</ServiceAgreementAccepted>
<ServiceAgreementAccepted>
<AgreementKey>765511</AgreementKey>
<AgreementType>INCLUDED</AgreementType>
<Amount>
<Cents>00</Cents>
<Doller>$45</Doller>
</Amount>
<Description>+ Support plan new 01</Description>
<Quantity>1</Quantity>
</ServiceAgreementAccepted>
<ServiceAgreementAccepted>
<AgreementKey>765512</AgreementKey>
<AgreementType>PREPAID</AgreementType>
<Amount>
<Cents>55</Cents>
<Doller>$1,500</Doller>
</Amount>
<Description>+ Rajesh V. Test Service Plan</Description>
<Quantity>1</Quantity>
</ServiceAgreementAccepted>
<Amount>
<Cents>00</Cents>
<Doller>$523,449</Doller>
</Amount>
<ServiceAgreementDeclined>
<AgreementKey>203871</AgreementKey>
<Description>- package 03</Description>
<Quantity>1</Quantity>
</ServiceAgreementDeclined>
<ServiceAgreementDeclined>
<AgreementKey>765514</AgreementKey>
<AgreementType>PREPAID</AgreementType>
<Description>- DECLINED : PowerGard Protection :Sprayer,R4045,New Units - still within basic warranty,Limited - Engine &amp; Powertrain,New - Grace Period: Under 95 days &amp; 100 hours,24 Total Months Or 1500 Total Hours,AU,500.00,13-Apr-2016</Description>
<Quantity>1</Quantity>
</ServiceAgreementDeclined>
<ServiceAgreementDeclined>
<AgreementKey>765510</AgreementKey>
<AgreementType>INCLUDED</AgreementType>
<Description>- Support plan new 03</Description>
<Quantity>1</Quantity>
</ServiceAgreementDeclined>
<ServiceAgreementDeclined>
<AgreementKey>765513</AgreementKey>
<AgreementType>PREPAID</AgreementType>
<Description>- Jayanti.G test JDSC</Description>
<Quantity>1</Quantity>
</ServiceAgreementDeclined>
<Option>
<Code>0230</Code>
<Description></Description>
<Quantity>1</Quantity>
</Option>
<Option>
<Code>0448</Code>
<Description></Description>
<Quantity>1</Quantity>
</Option>
<Option>
<Code>188I</Code>
<Description></Description>
<Quantity>1</Quantity>
</Option>
<Option>
<Code>2310</Code>
<Description></Description>
<Quantity>1</Quantity>
</Option>
<Option>
<Code>2410</Code>
<Description></Description>
<Quantity>1</Quantity>
</Option>
<Option>
<Code>2854</Code>
<Description></Description>
<Quantity>1</Quantity>
</Option>
<Option>
<Code>7060</Code>
<Description></Description>
<Quantity>1</Quantity>
</Option>
<Option>
<Code>3542</Code>
<Description></Description>
<Quantity>1</Quantity>
</Option>
<Option>
<Code>4115</Code>
<Description></Description>
<Quantity>1</Quantity>
</Option>
<Option>
<Code>4210</Code>
<Description></Description>
<Quantity>1</Quantity>
</Option>
<Option>
<Code>4300</Code>
<Description></Description>
<Quantity>1</Quantity>
</Option>
<Option>
<Code>4050</Code>
<Description></Description>
<Quantity>1</Quantity>
</Option>
<Option>
<Code>5175</Code>
<Description></Description>
<Quantity>1</Quantity>
</Option>
<Option>
<Code>5465</Code>
<Description></Description>
<Quantity>1</Quantity>
</Option>
<Option>
<Code>5500</Code>
<Description></Description>
<Quantity>1</Quantity>
</Option>
<Option>
<Code>7540</Code>
<Description></Description>
<Quantity>1</Quantity>
</Option>
<Option>
<Code>7825</Code>
<Description></Description>
<Quantity>1</Quantity>
</Option>
<Option>
<Code>7901</Code>
<Description></Description>
<Quantity>1</Quantity>
</Option>
<Option>
<Code>7925</Code>
<Description></Description>
<Quantity>1</Quantity>
</Option>
<ProductDescription>R4045 Self-Propelled Sprayer (Model Year 2016)</ProductDescription>
<TechnologyOptions>
<Code>1835</Code>
<Name></Name>
<Quantity>1</Quantity>
</TechnologyOptions>
<TechnologyOptions>
<Code>1845</Code>
<Name></Name>
<Quantity>1</Quantity>
</TechnologyOptions>
<TechnologyOptions>
<Code>1900</Code>
<Name></Name>
<Quantity>1</Quantity>
</TechnologyOptions>
</EquipmentDetail>
<isESignatureEnabled>false</isESignatureEnabled>
<MarketUse/>
<PONumber>8580</PONumber>
<PurchaseOrderSummary>
<Balance>
<Cents>10</Cents>
<Doller>$1,051,541</Doller>
</Balance>
<BalanceDue>
<Cents>21</Cents>
<Doller>$1,156,695</Doller>
</BalanceDue>
<CashWithOrder>
<Cents>00</Cents>
<Doller>$0</Doller>
</CashWithOrder>
<Tax>
<Amount>
<Cents>11</Cents>
<Doller>$105,154</Doller>
</Amount>
<Name>GST TAX</Name>
<Percent>10.0</Percent>
</Tax>
<RentalApplied>
<Cents>00</Cents>
<Doller>$0</Doller>
</RentalApplied>
<SubTotal>
<Cents>21</Cents>
<Doller>$1,156,695</Doller>
</SubTotal>
<SubTotalMinusGST>
<Cents>10</Cents>
<Doller>$1,051,541</Doller>
</SubTotalMinusGST>
<TotalEquipmentPrice>
<Cents>10</Cents>
<Doller>$1,051,541</Doller>
</TotalEquipmentPrice>
<TotalPayOff>
<Cents>00</Cents>
<Doller>$0</Doller>
</TotalPayOff>
<TotalTradeInAllowance>
<Cents>00</Cents>
<Doller>$0</Doller>
</TotalTradeInAllowance>
</PurchaseOrderSummary>
<Purchaser>
<Address>
<AddressLine1>303 BACK LANE</AddressLine1>
<City>JUNCTION HILL</City>
<Country>AU</Country>
<State>NSW</State>
<Zipcode>2460</Zipcode>
</Address>
<CustomerType>Individual</CustomerType>
<Email>latadkavita@johndeere.com</Email>
<JDProfileNumber>363800993</JDProfileNumber>
<Name>GARRY RAYMOND JOHNSTON</Name>
</Purchaser>
<PurchaserType/>
<quoteId>117994</quoteId>
<QuoteIdStr>117994</QuoteIdStr>
<Revision>2</Revision>
<revisionId>Revision2</revisionId>
<SalesPersonName>DAVID CHAFFEY</SalesPersonName>
<SellingDealership>
<Address>
<AddressLine1>LOT 7 MOORONG STREET</AddressLine1>
<City>WAGGA WAGGA</City>
<State>NSW</State>
<Zipcode>2650</Zipcode>
</Address>
<BranchCode>23</BranchCode>
<CityStateZip>WAGGA WAGGA 2650</CityStateZip>
<DealerAccount>230208</DealerAccount>
<IsCFDealer>N</IsCFDealer>
<Name>HUTCHEON &amp; PEARCE WAGGA</Name>
<PhoneNumber>123456</PhoneNumber>
</SellingDealership>
<showDetails>1</showDetails>
</POData>
</OrderForm>
